odoo10_addon_base_business_document_import-10.0.1.0.0.99.dev29-nspkg.pth
odoo/addons/base_business_document_import/README.rst
odoo/addons/base_business_document_import/__init__.py
odoo/addons/base_business_document_import/__manifest__.py
odoo/addons/base_business_document_import/i18n/base_business_document_import.pot
odoo/addons/base_business_document_import/i18n/es.po
odoo/addons/base_business_document_import/i18n/fr.po
odoo/addons/base_business_document_import/i18n/pt.po
odoo/addons/base_business_document_import/models/__init__.py
odoo/addons/base_business_document_import/models/business_document_import.py
odoo/addons/base_business_document_import/static/description/icon.png
odoo/addons/base_business_document_import/tests/__init__.py
odoo/addons/base_business_document_import/tests/test_business_document_import.py
odoo10_addon_base_business_document_import-10.0.1.0.0.99.dev29.dist-info/METADATA
odoo10_addon_base_business_document_import-10.0.1.0.0.99.dev29.dist-info/WHEEL
odoo10_addon_base_business_document_import-10.0.1.0.0.99.dev29.dist-info/namespace_packages.txt
odoo10_addon_base_business_document_import-10.0.1.0.0.99.dev29.dist-info/top_level.txt
odoo10_addon_base_business_document_import-10.0.1.0.0.99.dev29.dist-info/RECORD
