Metadata-Version: 2.1
Name: odoo10-addon-base-business-document-import
Version: 10.0.1.0.0.99.dev29
Summary: Provides technical tools to import sale orders or supplier invoices
Home-page: http://www.akretion.com
Author: Akretion,Odoo Community Association (OCA)
Author-email: support@odoo-community.org
License: AGPL-3
Platform: UNKNOWN
Classifier: Programming Language :: Python
Classifier: Framework :: Odoo
Classifier: License :: OSI Approved :: GNU Affero General Public License v3
Requires-Python: ~=2.7
Requires-Dist: PyPDF2
Requires-Dist: odoo10-addon-account-tax-unece
Requires-Dist: odoo10-addon-base-vat-sanitized
Requires-Dist: odoo10-addon-product-uom-unece
Requires-Dist: odoo (<10.1dev,>=10.0)
